nonebot_plugin_tsugu_frontend-0.1.1.dist-info/METADATA
nonebot_plugin_tsugu_frontend-0.1.1.dist-info/WHEEL
nonebot_plugin_tsugu_frontend/__init__.py
nonebot_plugin_tsugu_frontend/config.py
nonebot_plugin_tsugu_frontend-0.1.1.dist-info/RECORD
