Metadata-Version: 2.1
Name: nonebot-plugin-tsugu-frontend
Version: 0.1.1
Summary: 基于 tsugu-python-frontend 的 tsugu-bangdream-bot NoneBot 插件
Author-Email: zhaomaoniu <2667292003@qq.com>
License: MIT
Requires-Python: >=3.8
Requires-Dist: nonebot2>=2.2.1
Requires-Dist: nonebot-plugin-alconna>=0.42.4
Requires-Dist: tsugu>=0.6.0
Requires-Dist: nonebot-plugin-userinfo>=0.2.4
